LICENSE
README.md
setup.py
src/mdocs.py
src/config/__init__.py
src/config/config.ini
src/mdocs.egg-info/PKG-INFO
src/mdocs.egg-info/SOURCES.txt
src/mdocs.egg-info/dependency_links.txt
src/mdocs.egg-info/entry_points.txt
src/mdocs.egg-info/top_level.txt
src/modules/__init__.py
src/modules/config_functions.py
src/modules/creation_functions.py