Metadata-Version: 2.1
Name: mdocs
Version: 0.2.0
Summary: Allows to extract docstrings from Python functions to create a documentation file in Markdown format.
Home-page: https://github.com/rasamex/mdocs
Author: rasamex
Author-email: nomail@nomail.com
License: GPL-2.0 license
Platform: UNKNOWN
License-File: LICENSE
